README.md
setup.py
my_unique_rocket55555555555555.egg-info/PKG-INFO
my_unique_rocket55555555555555.egg-info/SOURCES.txt
my_unique_rocket55555555555555.egg-info/dependency_links.txt
my_unique_rocket55555555555555.egg-info/top_level.txt
rocket/__init__.py
rocket/rocket.py
rocket/setup.py