Metadata-Version: 2.1
Name: my_unique_rocket55555555555555
Version: 1.0.0
Summary: An awesome package that does something
Home-page: http://pypi.python.org/pypi/my_unique_rocket/
Author: aymen
Author-email: your_email@example.com
License: LICENSE.txt
